eukcc/__init__.py
eukcc/__main__.py
eukcc/base.py
eukcc/bin.py
eukcc/eukcc.py
eukcc/exec.py
eukcc/fasta.py
eukcc/file.py
eukcc/find_markerset.py
eukcc/helper.py
eukcc/refine.py
eukcc/set_define.py
eukcc/treehandler.py
eukcc/version.py
eukcc-2.1.3.data/scripts/binlinks.py
eukcc-2.1.3.data/scripts/filter_euk_bins.py
scripts/binlinks.py
scripts/filter_euk_bins.py
eukcc-2.1.3.dist-info/METADATA
eukcc-2.1.3.dist-info/WHEEL
eukcc-2.1.3.dist-info/entry_points.txt
eukcc-2.1.3.dist-info/top_level.txt
eukcc-2.1.3.dist-info/RECORD
