Metadata-Version: 2.1
Name: eukcc
Version: 2.1.3
Summary: Check eukaryotic genomes or MAGs for completeness and contamination
Home-page: https://github.com/Finn-Lab/EukCC/
Author: Paul Saary
Author-email: Paul Saary <eukcc@paulsaary.de>, MGnify team <metagenomics-help@ebi.ac.uk>
License: GPLv3
Keywords: bioinformatics,mags,eukaryotic,completeness,contamination
Classifier: Programming Language :: Python :: 3.6
Classifier: License :: OSI Approved :: GNU General Public License v3 (GPLv3)
Classifier: Operating System :: Unix
Requires-Python: >=3.6
Requires-Dist: ete3 >=3.1.3
Requires-Dist: numpy >=1.24.4
Requires-Dist: jsonpickle >=4.0.0
Requires-Dist: biopython ==1.83
Requires-Dist: pysam ==0.21.0
Requires-Dist: six
Provides-Extra: dev
Requires-Dist: pre-commit ==3.8.0 ; extra == 'dev'
Requires-Dist: black ==24.8.0 ; extra == 'dev'
Requires-Dist: flake8 ==7.1.1 ; extra == 'dev'
Requires-Dist: pep8-naming ==0.14.1 ; extra == 'dev'
Provides-Extra: tests
Requires-Dist: pytest ==7.4.0 ; extra == 'tests'
Requires-Dist: pytest-md ==0.2.0 ; extra == 'tests'
Requires-Dist: pytest-workflow ==2.0.1 ; extra == 'tests'
Requires-Dist: ete3 >=3.1.3 ; extra == 'tests'
Requires-Dist: numpy >=1.24.4 ; extra == 'tests'
Requires-Dist: jsonpickle >=4.0.0 ; extra == 'tests'
Requires-Dist: biopython ==1.83 ; extra == 'tests'
Requires-Dist: pysam ==0.21.0 ; extra == 'tests'
Requires-Dist: six ; extra == 'tests'
